[{
	"Date": "6/13/2015",
	"Start Time": "11:53 AM",
	"Call Duration": 10,
	"Time Duration": "0:10",
	"End Time": "12:03 PM"
}, {
	"Date": "6/13/2015",
	"Start Time": "12:39 PM",
	"Call Duration": 7,
	"Time Duration": "0:07",
	"End Time": "12:46 PM"
}, {
	"Date": "6/13/2015",
	"Start Time": "1:27 PM",
	"Call Duration": 1,
	"Time Duration": "0:01",
	"End Time": "1:28 PM"
}, {
	"Date": "6/13/2015",
	"Start Time": "1:37 PM",
	"Call Duration": 4,
	"Time Duration": "0:04",
	"End Time": "1:41 PM"
}, {
	"Date": "6/13/2015",
	"Start Time": "2:42 PM",
	"Call Duration": 3,
	"Time Duration": "0:03",
	"End Time": "2:45 PM"
}]